tagify_widget/__init__.py
tagify_widget/widgets.py
tagify_widget/static/tagify_widget/vender/tagify/tagify.css
tagify_widget/static/tagify_widget/vender/tagify/tagify.min.js
tagify_widget/static/tagify_widget/vender/tagify/tagify.polyfills.min.js
tagify_widget/templates/tagify_widget/select.html
tagify_widget/templates/tagify_widget/select_multiple.html
django_tagify_widget-0.1.3.dist-info/METADATA
django_tagify_widget-0.1.3.dist-info/WHEEL
django_tagify_widget-0.1.3.dist-info/top_level.txt
django_tagify_widget-0.1.3.dist-info/RECORD
